openmm_torch_unofficial_cpu-1.5.dist-info/RECORD
openmm_torch_unofficial_cpu-1.5.dist-info/WHEEL
openmm_torch_unofficial_cpu-1.5.dist-info/top_level.txt
openmm_torch_unofficial_cpu-1.5.dist-info/METADATA
openmmtorch/openmmtorch.py
openmmtorch/__init__.py
openmmtorch/TorchPluginWrapper.cpp
openmmtorch/_openmmtorch.cpython-310-darwin.so
openmmtorch/include/TorchForce.h
openmmtorch/include/TorchKernels.h
openmmtorch/include/internal/TorchForceImpl.h
openmmtorch/include/internal/windowsExportTorch.h
openmm/lib/libOpenMMTorch.dylib
openmm/lib/plugins/libOpenMMTorchReference.dylib
openmm/lib/plugins/libOpenMMTorchOpenCL.dylib
